proactiveagent/__init__.py
proactiveagent/agent.py
proactiveagent/scheduler.py
proactiveagent/utils.py
proactiveagent/decision_engines/README.md
proactiveagent/decision_engines/__init__.py
proactiveagent/decision_engines/ai_based.py
proactiveagent/decision_engines/base.py
proactiveagent/decision_engines/function_based.py
proactiveagent/decision_engines/simple.py
proactiveagent/decision_engines/threshold_based.py
proactiveagent/providers/__init__.py
proactiveagent/providers/base.py
proactiveagent/providers/openai_provider.py
proactiveagent/sleep_time_calculators/README.md
proactiveagent/sleep_time_calculators/__init__.py
proactiveagent/sleep_time_calculators/ai_based.py
proactiveagent/sleep_time_calculators/base.py
proactiveagent/sleep_time_calculators/function_based.py
proactiveagent/sleep_time_calculators/pattern_based.py
proactiveagent/sleep_time_calculators/static.py
proactiveagent-0.1.1.dist-info/METADATA
proactiveagent-0.1.1.dist-info/WHEEL
proactiveagent-0.1.1.dist-info/licenses/LICENSE
proactiveagent-0.1.1.dist-info/RECORD
