Metadata-Version: 2.4
Name: proactiveagent
Version: 0.1.1
Summary: A Python framework to transform your AI from reactive to proactive with intelligent timing and context-aware wake-up patterns - Your agent decides when to speak!
Project-URL: Homepage, https://github.com/leomariga/ProactiveAgent
Project-URL: Repository, https://github.com/leomariga/ProactiveAgent
Project-URL: Documentation, https://leomariga.github.io/ProactiveAgent/
Project-URL: Issues, https://github.com/leomariga/ProactiveAgent/issues
Author-email: Leonardo Mariga <leomariga@gmail.com>
Maintainer-email: Leonardo Mariga <leomariga@gmail.com>
License: BSD-3-Clause
License-File: LICENSE
Keywords: active,agent,ai,automation,autonomous,chatbot,context-aware,conversational,decision-making,gpt,intelligent,llm,openai,proactive,scheduling,thread,timing
Classifier: Development Status :: 5 - Production/Stable
Classifier: Intended Audience :: Developers
Classifier: License :: OSI Approved :: BSD License
Classifier: Operating System :: OS Independent
Classifier: Programming Language :: Python :: 3
Classifier: Programming Language :: Python :: 3.12
Classifier: Programming Language :: Python :: 3.13
Classifier: Topic :: Communications :: Chat
Classifier: Topic :: Communications :: Conferencing
Classifier: Topic :: Scientific/Engineering :: Artificial Intelligence
Classifier: Topic :: Scientific/Engineering :: Human Machine Interfaces
Classifier: Topic :: Scientific/Engineering :: Information Analysis
Classifier: Topic :: Software Development :: Libraries :: Python Modules
Requires-Python: >=3.12
Requires-Dist: openai>=1.108.0
